osm_fieldwork/OdkCentral.py
osm_fieldwork/OdkCentralAsync.py
osm_fieldwork/__init__.py
osm_fieldwork/__version__.py
osm_fieldwork/enums.py
osm_fieldwork/update_xlsform.py
osm_fieldwork/xforms.yaml
osm_fieldwork/data_models/__init__.py
osm_fieldwork/data_models/amenities.yaml
osm_fieldwork/data_models/buildings.yaml
osm_fieldwork/data_models/camping.yaml
osm_fieldwork/data_models/category.yaml
osm_fieldwork/data_models/cemeteries.yaml
osm_fieldwork/data_models/education.yaml
osm_fieldwork/data_models/emergency.yaml
osm_fieldwork/data_models/health.yaml
osm_fieldwork/data_models/highways.yaml
osm_fieldwork/data_models/landusage.yaml
osm_fieldwork/data_models/models.yaml
osm_fieldwork/data_models/nature.yaml
osm_fieldwork/data_models/places.yaml
osm_fieldwork/data_models/religious.yaml
osm_fieldwork/data_models/toilets.yaml
osm_fieldwork/data_models/wastedisposal.yaml
osm_fieldwork/data_models/waterpoints.yaml
osm_fieldwork/data_models/waterways.yaml
osm_fieldwork/form_components/__init__.py
osm_fieldwork/form_components/choice_fields.py
osm_fieldwork/form_components/digitisation_fields.py
osm_fieldwork/form_components/mandatory_fields.py
osm_fieldwork/form_components/translations/__init__.py
osm_fieldwork/form_components/translations/cs.json
osm_fieldwork/form_components/translations/en.json
osm_fieldwork/form_components/translations/es.json
osm_fieldwork/form_components/translations/fr.json
osm_fieldwork/form_components/translations/it.json
osm_fieldwork/form_components/translations/ja.json
osm_fieldwork/form_components/translations/ne.json
osm_fieldwork/form_components/translations/pt-BR.json
osm_fieldwork/form_components/translations/sw.json
osm_fieldwork/json_data_models/__init__.py
osm_fieldwork/json_data_models/amenities.json
osm_fieldwork/json_data_models/buildings.json
osm_fieldwork/json_data_models/camping.json
osm_fieldwork/json_data_models/category.json
osm_fieldwork/json_data_models/cemeteries.json
osm_fieldwork/json_data_models/education.json
osm_fieldwork-0.23.0.dist-info/METADATA
osm_fieldwork-0.23.0.dist-info/WHEEL
osm_fieldwork-0.23.0.dist-info/entry_points.txt
osm_fieldwork-0.23.0.dist-info/licenses/LICENSE.md
osm_fieldwork-0.23.0.dist-info/RECORD
