Metadata-Version: 2.4
Name: osm-fieldwork
Version: 0.23.0
Summary: Processing field data from ODK to OpenStreetMap format.
Project-URL: homepage, https://hotosm.github.io/osm-fieldwork
Project-URL: documentation, https://hotosm.github.io/osm-fieldwork
Project-URL: repository, https://github.com/hotosm/field-tm/blob/main/src/backend/packages/osm-fieldwork
Author-email: Rob Savoye <rob.savoye@hotosm.org>, Sam Woodcock <sam.woodcock@hotosm.org>, Sujan Adhikari <adhikarisujan.naxa@gmail.com>, Anuj Gupta <anuj.naxa@gmail.com>
License-Expression: GPL-3.0-only
License-File: LICENSE.md
Keywords: fmtm,hot,odk,openstreetmap
Classifier: Programming Language :: Python :: 3
Classifier: Programming Language :: Python :: 3.10
Classifier: Programming Language :: Python :: 3.11
Classifier: Programming Language :: Python :: 3.12
Classifier: Topic :: Scientific/Engineering :: GIS
Classifier: Topic :: Utilities
Requires-Python: >=3.10
Requires-Dist: aiohttp>=3.8.4
Requires-Dist: geojson>=3.0.0
Requires-Dist: openpyxl>=3.0.10
Requires-Dist: osm-rawdata>=0.1.7
Requires-Dist: pandas>=1.5.0
Requires-Dist: python-calamine>=0.3.1
Requires-Dist: pyyaml>=6.0.0
Requires-Dist: requests>=2.26.0
Requires-Dist: segno>=1.5.2
